uurest/__init__.py
uurest/common.py
uurest/generaltypes.py
uurest/ioutils.py
uurest/logging.py
uurest/multipartEncoder.py
uurest/stopwatch.py
uurest/uuRestLogin.py
uurest/uucommand.py
uurest/uufetch.py
uurest/init/__init__.py
uurest/init/init.py
uurest/init/init_files.py
uurest-1.0.25.dist-info/METADATA
uurest-1.0.25.dist-info/WHEEL
uurest-1.0.25.dist-info/top_level.txt
uurest-1.0.25.dist-info/RECORD
