Metadata-Version: 2.1
Name: uurest
Version: 1.0.25
Summary: uuRest library and its two main functions "call" and "fetch" are designed to allow users to rapidly scrape/automate web applications designed and developed by Unicorn Systems (Unicorn.com).
Home-page: UNKNOWN
Author: Jaromir Sivic
Author-email: unknown@unknown.com
License: MIT
Keywords: python,uuRest,Unicorn Systems,UAF,Unicorn Application Framework
Platform: UNKNOWN
Classifier: License :: OSI Approved :: MIT License
Classifier: Programming Language :: Python :: 3.8
Classifier: Operating System :: OS Independent
Requires-Python: >=3.8
Requires-Dist: requests
Provides-Extra: dev
Requires-Dist: twine (>=4.0.2) ; extra == 'dev'
